LICENSE
MANIFEST.in
README.md
setup.py
libtecnoan/__init__.py
libtecnoan/github_api.py
libtecnoan.egg-info/PKG-INFO
libtecnoan.egg-info/SOURCES.txt
libtecnoan.egg-info/dependency_links.txt
libtecnoan.egg-info/not-zip-safe
libtecnoan.egg-info/requires.txt
libtecnoan.egg-info/top_level.txt